__init__.py
handlers.py
main.py
platform_handler.py
requests_wrapper.py
ssh_ca_cli-0.13.8.dist-info/METADATA
ssh_ca_cli-0.13.8.dist-info/WHEEL
ssh_ca_cli-0.13.8.dist-info/entry_points.txt
ssh_ca_cli-0.13.8.dist-info/RECORD
