Metadata-Version: 2.1
Name: ssh-ca-cli
Version: 0.13.8
Summary: CLI client to generate SSH Certificates
Author: Ric Sapasap
Author-email: ric.sapasap@geant.org
Requires-Python: >=3.9,<4.0
Classifier: Programming Language :: Python :: 3
Classifier: Programming Language :: Python :: 3.9
Classifier: Programming Language :: Python :: 3.10
Classifier: Programming Language :: Python :: 3.11
Classifier: Programming Language :: Python :: 3.12
Requires-Dist: certifi (>=2024.2.2,<2025.0.0)
Requires-Dist: qrcode (>=7.4.2,<8.0.0)
